AUTHORS.rst
CONTRIBUTING.rst
HISTORY.rst
LICENSE
MANIFEST.in
README.rst
setup.cfg
setup.py
redis_protocol/__init__.py
redis_protocol/protocol.py
redis_protocol.egg-info/PKG-INFO
redis_protocol.egg-info/SOURCES.txt
redis_protocol.egg-info/dependency_links.txt
redis_protocol.egg-info/not-zip-safe
redis_protocol.egg-info/pbr.json
redis_protocol.egg-info/top_level.txt