Metadata-Version: 1.1
Name: redis-protocol
Version: 0.0.2
Summary: Redis Protocol implemented by python
Home-page: https://github.com/youngking/redis_protocol
Author: Young King
Author-email: yanckin@gmail.com
License: BSD
Keywords: redis_protocol
Platform: UNKNOWN
Classifier: Development Status :: 2 - Pre-Alpha
Classifier: Intended Audience :: Developers
Classifier: License :: OSI Approved :: BSD License
Classifier: Natural Language :: English
Classifier: Programming Language :: Python :: 2
Classifier: Programming Language :: Python :: 2.6
Classifier: Programming Language :: Python :: 2.7
Classifier: Programming Language :: Python :: 3
Classifier: Programming Language :: Python :: 3.3
